hwcomponents_library/__init__.py
hwcomponents_library/_version.py
hwcomponents_library/base.py
hwcomponents_library/library/__init__.py
hwcomponents_library/library/aladdin.py
hwcomponents_library/library/atomlayer.py
hwcomponents_library/library/brahms.py
hwcomponents_library/library/dummy.py
hwcomponents_library/library/forms.py
hwcomponents_library/library/isaac.py
hwcomponents_library/library/jia.py
hwcomponents_library/library/misc.py
hwcomponents_library/library/newton.py
hwcomponents_library/library/raella.py
hwcomponents_library/library/timely.py
hwcomponents_library/library/wan.py
hwcomponents_library-1.0.39.dist-info/METADATA
hwcomponents_library-1.0.39.dist-info/WHEEL
hwcomponents_library-1.0.39.dist-info/top_level.txt
hwcomponents_library-1.0.39.dist-info/RECORD
