Metadata-Version: 2.4
Name: hwcomponents_library
Version: 1.0.39
Summary: A library of hardware components for energy estimation.
Author-email: Tanner Andrulis <Andrulis@Mit.edu>
License-Expression: MIT
Keywords: hardware,components,energy,estimation
Classifier: Development Status :: 3 - Alpha
Classifier: Programming Language :: Python :: 3
Classifier: Topic :: Scientific/Engineering :: Electronic Design Automation (EDA)
Requires-Python: >=3.12
Requires-Dist: hwcomponents
Requires-Dist: hwcomponents-cacti
